zirconium/__init__.py
zirconium/config.py
zirconium/parsers.py
zirconium/sproviders.py
zirconium/utils.py
zirconium-1.2.4.dist-info/LICENSE
zirconium-1.2.4.dist-info/METADATA
zirconium-1.2.4.dist-info/WHEEL
zirconium-1.2.4.dist-info/top_level.txt
zirconium-1.2.4.dist-info/RECORD
