Metadata-Version: 2.1
Name: zirconium
Version: 1.2.4
Summary: Excellent configuration management for Python
Home-page: https://github.com/turnbullerin/zirconium
Author: Erin Turnbull
Author-email: erin.a.turnbull@gmail.com
Project-URL: Bug Tracker, https://github.com/turnbullerin/zirconium/issues
Classifier: Programming Language :: Python :: 3
Classifier: License :: OSI Approved :: MIT License
Classifier: Operating System :: OS Independent
Requires-Python: >=3.7
License-File: LICENSE
